speclite_cli/__init__.py
speclite_cli/__main__.py
speclite_cli/scripts/bash/check-prerequisites.sh
speclite_cli/scripts/bash/common.sh
speclite_cli/scripts/bash/create-new-feature.sh
speclite_cli/scripts/bash/setup-plan.sh
speclite_cli/scripts/bash/update-agent-context.sh
speclite_cli/scripts/powershell/check-prerequisites.ps1
speclite_cli/scripts/powershell/common.ps1
speclite_cli/scripts/powershell/create-new-feature.ps1
speclite_cli/scripts/powershell/setup-plan.ps1
speclite_cli/scripts/powershell/update-agent-context.ps1
speclite_cli/templates/agent-file-template.md
speclite_cli/templates/checklist-template.md
speclite_cli/templates/constitution-template.md
speclite_cli/templates/plan-template.md
speclite_cli/templates/review-template.md
speclite_cli/templates/spec-template.md
speclite_cli/templates/tasks-template.md
speclite_cli/templates/vscode-settings.json
speclite_cli/templates/commands/analyze.md
speclite_cli/templates/commands/checklist.md
speclite_cli/templates/commands/clarify.md
speclite_cli/templates/commands/constitution.md
speclite_cli/templates/commands/implement.md
speclite_cli/templates/commands/plan.md
speclite_cli/templates/commands/review.md
speclite_cli/templates/commands/specify.md
speclite_cli/templates/commands/tasks.md
speclite_cli/templates/commands/taskstoissues.md
speclite_cli-0.0.10.dist-info/METADATA
speclite_cli-0.0.10.dist-info/WHEEL
speclite_cli-0.0.10.dist-info/entry_points.txt
speclite_cli-0.0.10.dist-info/licenses/LICENSE
speclite_cli-0.0.10.dist-info/RECORD
