Metadata-Version: 2.4
Name: speclite-cli
Version: 0.0.10
Summary: SpecLite – A Pragmatic Evolution of Spec Kit for Spec-Driven Development
Project-URL: Homepage, https://github.com/speclite-dev/speclite
Project-URL: Repository, https://github.com/speclite-dev/speclite
Project-URL: Changelog, https://github.com/speclite-dev/speclite/blob/main/CHANGELOG.md
Author: Bret Johnson
License: MIT License
License-File: LICENSE
Keywords: cli,sdd,spec-driven-development,specification
Classifier: Development Status :: 3 - Alpha
Classifier: Environment :: Console
Classifier: Intended Audience :: Developers
Classifier: License :: OSI Approved :: MIT License
Classifier: Programming Language :: Python :: 3
Classifier: Programming Language :: Python :: 3 :: Only
Classifier: Programming Language :: Python :: 3.11
Classifier: Programming Language :: Python :: 3.12
Classifier: Programming Language :: Python :: 3.13
Classifier: Topic :: Software Development
Requires-Python: >=3.11
Requires-Dist: platformdirs
Requires-Dist: readchar
Requires-Dist: rich
Requires-Dist: typer
